{
  "articles": [
    {
      "title": "mj",
      "shortDescription": "hahahahaha",
      "longDescription": "hahahahahahahahaha",
      "id": 3
    },
    {
      "title": "Sir Khalil",
      "shortDescription": "dasd",
      "longDescription": "asdasdasd",
      "id": 4
    },
    {
      "title": "sadsad",
      "shortDescription": "sada",
      "longDescription": "sdasd",
      "id": 5
    },
    {
      "title": "mj123",
      "shortDescription": "dasdas",
      "longDescription": "dasddasd",
      "id": 6
    }
  ]
}